ftarc/__init__.py
ftarc/cli/__init__.py
ftarc/cli/main.py
ftarc/cli/pipeline.py
ftarc/cli/util.py
ftarc/static/example_ftarc.yml
ftarc/static/urls.yml
ftarc/task/__init__.py
ftarc/task/bwa.py
ftarc/task/controller.py
ftarc/task/core.py
ftarc/task/downloader.py
ftarc/task/fastqc.py
ftarc/task/gatk.py
ftarc/task/picard.py
ftarc/task/resource.py
ftarc/task/samtools.py
ftarc/task/trimgalore.py
ftarc/template/luigi.log.cfg.j2
ftarc-0.2.4.dist-info/LICENSE
ftarc-0.2.4.dist-info/METADATA
ftarc-0.2.4.dist-info/WHEEL
ftarc-0.2.4.dist-info/entry_points.txt
ftarc-0.2.4.dist-info/top_level.txt
ftarc-0.2.4.dist-info/RECORD
